transpector/__init__.py
transpector/__main__.py
transpector/jupyter_server_config.py
transpector/launch.py
transpector/main.py
transpector/model.py
transpector/frontend_dist/.DS_Store
transpector/frontend_dist/404.html
transpector/frontend_dist/favicon.ico
transpector/frontend_dist/index.html
transpector/frontend_dist/_next/static/chunks/08548717-255a240eeda86295.js
transpector/frontend_dist/_next/static/chunks/0e226fb0-0ffa81597ede903e.js
transpector/frontend_dist/_next/static/chunks/0f7a40cd.b588aa398396b85f.js
transpector/frontend_dist/_next/static/chunks/1053.adb29a47c34b267a.js
transpector/frontend_dist/_next/static/chunks/1084.8bd09a422bf924f1.js
transpector/frontend_dist/_next/static/chunks/1390.ba90fcba98c196ac.js
transpector/frontend_dist/_next/static/chunks/1426.873d7ab40d9ecad4.js
transpector/frontend_dist/_next/static/chunks/1446.729b459281b981b9.js
transpector/frontend_dist/_next/static/chunks/1448.4cb302a7eed94256.js
transpector/frontend_dist/_next/static/chunks/1650.06a77268379b94b2.js
transpector/frontend_dist/_next/static/chunks/1660.76cc05d00e5034ad.js
transpector/frontend_dist/_next/static/chunks/177.e4e8e92e618e66e8.js
transpector/frontend_dist/_next/static/chunks/1770.ffd38031b937c10a.js
transpector/frontend_dist/_next/static/chunks/1873.ad239337a916524b.js
transpector/frontend_dist/_next/static/chunks/1920.e6bf04b81039b68b.js
transpector/frontend_dist/_next/static/chunks/2016.8b2b4ce7334096dd.js
transpector/frontend_dist/_next/static/chunks/2040.2b48b43e5c9bbd94.js
transpector/frontend_dist/_next/static/chunks/2119.0cb64fe9bc609787.js
transpector/frontend_dist/_next/static/chunks/2136.3c7248e1cb33b0f2.js
transpector/frontend_dist/_next/static/chunks/228.bcd421992bab4a0b.js
transpector/frontend_dist/_next/static/chunks/2314.ce3a0e1828ad2d06.js
transpector/frontend_dist/_next/static/chunks/2386.d1eeedc6355d2049.js
transpector/frontend_dist/_next/static/chunks/2406.04743ed8b26fbb4f.js
transpector-0.1.6.dist-info/METADATA
transpector-0.1.6.dist-info/WHEEL
transpector-0.1.6.dist-info/entry_points.txt
transpector-0.1.6.dist-info/top_level.txt
transpector-0.1.6.dist-info/RECORD
