Metadata-Version: 2.1
Name: transpector
Version: 0.1.6
Summary: Visually inspect, analyse and debug transformer models. Aimed at reducing cycle times for interpretability research and lowering the barrier to entry.
Author: Rob Kopel
License: LICENSE
Requires-Dist: fastapi
Requires-Dist: uvicorn[standard]
Requires-Dist: transformer-lens
Requires-Dist: circuitsvis
Requires-Dist: einops
Requires-Dist: fancy-einsum
Requires-Dist: torchtyping
Requires-Dist: jupyterlab
Requires-Dist: nbclient
Requires-Dist: websockets
Requires-Dist: jaxtyping
